urlx/__init__.py
urlx/strenum.py
urlx/url.py
urlx/url_enums/__init__.py
urlx/url_enums/port.py
urlx/url_enums/protocol.py
urlx-1.0.1.dist-info/LICENSE
urlx-1.0.1.dist-info/WHEEL
urlx-1.0.1.dist-info/METADATA
urlx-1.0.1.dist-info/RECORD
