Metadata-Version: 2.1
Name: urlx
Version: 1.0.1
Summary: The purpose of this package is to standardize URL declaration in the codebase
Home-page: https://volodymyrbor.github.io/urlx/
License: MIT
Author: volodymyrb
Author-email: volodymyr.borysiuk0@gmail.com
Requires-Python: >=3.10,<4.0
Classifier: License :: OSI Approved :: MIT License
Classifier: Programming Language :: Python :: 3
Classifier: Programming Language :: Python :: 3.10
Classifier: Programming Language :: Python :: 3.11
Project-URL: Documentation, https://volodymyrbor.github.io/urlx/
Project-URL: Repository, https://github.com/VolodymyrBor/urlx
